{
    "title": "Birds that combine speed and force",
    "image": {
        "uri": "https://iiif.elifesciences.org/lax:13544/elife-13544-fig1-v1.tif",
        "source": {
            "mediaType": "image/jpeg",
            "filename": "elife-13544-fig1-v1.tif",
            "uri": "https://iiif.elifesciences.org/lax:13544/elife-13544-fig1-v1.tif/full/full/0/default.jpg"
        },
        "size": {
            "height": 1894,
            "width": 4300
        },
        "alt": ""
    },
    "item": {
        "status": "vor",
        "stage": "published",
        "id": "13544",
        "version": 1,
        "type": "research-article",
        "doi": "10.7554/eLife.13544",
        "authorLine": "Matthew J Fuxjager et al.",
        "title": "Select forelimb muscles have evolved superfast contractile speed to support acrobatic social displays",
        "published": "2016-04-12T00:00:00Z",
        "versionDate": "2016-04-12T00:00:00Z",
        "statusDate": "2016-04-12T00:00:00Z",
        "volume": 2,
        "elocationId": "e13544",
        "pdf": "https://elife-publishing-cdn.s3.amazonaws.com/13544/elife-13544-v1.pdf",
        "subjects": [
            {
                "id": "ecology",
                "name": "Ecology"
            },
            {
                "id": "Neuroscience",
                "name": "neuroscience"
            }
        ]
    }
}
