{
    "number": 1,
    "title": "June 2013",
    "impactStatement": "Welcome to the first eLife podcast, which covers topics as diverse as the origins of multicellularity, what modern sequencing technology can tell us about the potato famines of the 1840s, the discovery of the receptor for the hepatitis B and D viruses, the effect of fog on the behaviour of car drivers, and the evolution of chromatin.",
    "published": "2013-07-17T08:30:27+00:00",
    "image": {
        "alt": "",
        "sizes": {
            "2:1": {
                "900": "%base_url%/images/podcast-episodes/1/jpg?width=900&height=450",
                "1800": "%base_url%/images/podcast-episodes/1/jpg?width=1800&height=900"
            },
            "16:9": {
                "250": "%base_url%/images/podcast-episodes/1/jpg?width=250&height=141",
                "500": "%base_url%/images/podcast-episodes/1/jpg?width=500&height=281"
            },
            "1:1": {
                "70": "%base_url%/images/podcast-episodes/1/jpg?width=70&height=70",
                "140": "%base_url%/images/podcast-episodes/1/jpg?width=140&height=140"
            }
        }
    },
    "mp3": "https://nakeddiscovery.com/libsyn/eLife_Podcast_13.06.mp3",
    "subjects": [
        "cell-biology",
        "genomics-evolutionary-biology"
    ]
}
