{
    "number": 2,
    "title": "July 2013",
    "impactStatement": "In this issue of the eLife podcast we discuss plants performing arithmetic division, the evolutionary dynamics of cancer, single-molecule measurements in the immune system, why blood vessels don’t grow in the retina, how to make science count in government, a sensor for ammonium, and the evolution of gene regulation.",
    "published": "2013-07-17T08:33:32+00:00",
    "image": {
        "alt": "",
        "sizes": {
            "2:1": {
                "900": "%base_url%/images/podcast-episodes/2/jpg?width=900&height=450",
                "1800": "%base_url%/images/podcast-episodes/2/jpg?width=1800&height=900"
            },
            "16:9": {
                "250": "%base_url%/images/podcast-episodes/2/jpg?width=250&height=141",
                "500": "%base_url%/images/podcast-episodes/2/jpg?width=500&height=281"
            },
            "1:1": {
                "70": "%base_url%/images/podcast-episodes/2/jpg?width=70&height=70",
                "140": "%base_url%/images/podcast-episodes/2/jpg?width=140&height=140"
            }
        }
    },
    "mp3": "https://nakeddiscovery.com/libsyn/eLife_Podcast_13.07.mp3",
    "subjects": [
        "plant-biology",
        "genomics-evolutionary-biology"
    ]
}
